awesome/__init__.py
package/__init__.py
package/mod.py
package/test/__init__.py
package/test/module_1.py
socialAD/__init__.py
socialAD/forward.py
socialAD/forwardAD.py
socialAD/forward_pro.py
socialAD/gradient.py
socialAD/root_finding.py
socialAD/toydiff.py
socialAD/test/__init__.py
socialAD/test/module_1.py
socialAD-0.1.23.dist-info/.DS_Store
socialAD-0.1.23.dist-info/METADATA
socialAD-0.1.23.dist-info/WHEEL
socialAD-0.1.23.dist-info/top_level.txt
socialAD-0.1.23.dist-info/RECORD
