Metadata-Version: 2.1
Name: socialAD
Version: 0.1.23
Summary: Automatic differentiation
Home-page: https://github.com/climate-change-is-real-python-dev/cs107-FinalProject
Author: Ju Chulakadabba, Tao Tsui, Jenny Wang, Dash Young-Saver
Author-email: ywang1@hsph.harvard.edu
License: UNKNOWN
Platform: UNKNOWN
Classifier: Programming Language :: Python :: 3
Classifier: License :: OSI Approved :: MIT License
